{
  "globalLastUpdatedAt": "2026-01-16T17:16:24.978Z",
  "players": [
    {
      "id": "p1",
      "displayName": "Vincent",
      "platform": "euw1",
      "riotId": {
        "gameName": "DarwinimAldi",
        "tagLine": "KASSE"
      },
      "puuid": "aJplVvbMXIsCsWtK-yt3uiCKOF0ZMIxCG0Kg8aF1JHOgHo7rTN4b3IAjBMvLUITS-ueJTbNoSgCsMA",
      "lastRank": {
        "tier": "BRONZE",
        "division": "III",
        "lp": 19,
        "wins": 7,
        "losses": 6,
        "winrate": 53.8
      },
      "currentRank": {
        "tier": "BRONZE",
        "division": "III",
        "lp": 19,
        "wins": 7,
        "losses": 6,
        "winrate": 53.8
      },
      "bans": [
        {
          "time": "2026-01-14T12:34:56.000Z",
          "champion": "Caitlyn",
          "note": "Von Bronze 4 nach 3"
        }
      ],
      "pendingBan": null,
      "lastUpdatedAt": "2026-01-16T17:16:24.978Z",
      "champGamesByYear": {
        "2026": {
          "computedAt": "2026-01-16T16:54:39.099Z",
          "year": 2026,
          "queueId": 420,
          "matchCount": 13,
          "totalGames": 13,
          "latestMatchId": "EUW1_7685543426",
          "countsByChampionId": {
            "9": 1,
            "11": 1,
            "15": 1,
            "18": 1,
            "20": 1,
            "21": 1,
            "51": 3,
            "64": 1,
            "103": 1,
            "113": 1,
            "202": 1
          },
          "byChampion": [
            {
              "championId": 51,
              "count": 3,
              "name": "Caitlyn",
              "icon": "https://ddragon.leagueoflegends.com/cdn/16.1.1/img/champion/Caitlyn.png"
            },
            {
              "championId": 9,
              "count": 1,
              "name": "Fiddlesticks",
              "icon": "https://ddragon.leagueoflegends.com/cdn/16.1.1/img/champion/Fiddlesticks.png"
            },
            {
              "championId": 11,
              "count": 1,
              "name": "Master Yi",
              "icon": "https://ddragon.leagueoflegends.com/cdn/16.1.1/img/champion/MasterYi.png"
            },
            {
              "championId": 15,
              "count": 1,
              "name": "Sivir",
              "icon": "https://ddragon.leagueoflegends.com/cdn/16.1.1/img/champion/Sivir.png"
            },
            {
              "championId": 18,
              "count": 1,
              "name": "Tristana",
              "icon": "https://ddragon.leagueoflegends.com/cdn/16.1.1/img/champion/Tristana.png"
            },
            {
              "championId": 20,
              "count": 1,
              "name": "Nunu & Willump",
              "icon": "https://ddragon.leagueoflegends.com/cdn/16.1.1/img/champion/Nunu.png"
            },
            {
              "championId": 21,
              "count": 1,
              "name": "Miss Fortune",
              "icon": "https://ddragon.leagueoflegends.com/cdn/16.1.1/img/champion/MissFortune.png"
            },
            {
              "championId": 64,
              "count": 1,
              "name": "Lee Sin",
              "icon": "https://ddragon.leagueoflegends.com/cdn/16.1.1/img/champion/LeeSin.png"
            },
            {
              "championId": 103,
              "count": 1,
              "name": "Ahri",
              "icon": "https://ddragon.leagueoflegends.com/cdn/16.1.1/img/champion/Ahri.png"
            },
            {
              "championId": 113,
              "count": 1,
              "name": "Sejuani",
              "icon": "https://ddragon.leagueoflegends.com/cdn/16.1.1/img/champion/Sejuani.png"
            },
            {
              "championId": 202,
              "count": 1,
              "name": "Jhin",
              "icon": "https://ddragon.leagueoflegends.com/cdn/16.1.1/img/champion/Jhin.png"
            }
          ],
          "triggerSoloTotal": 13
        }
      },
      "last5": {
        "computedAt": "2026-01-16T16:54:38.745Z",
        "games": [
          {
            "matchId": "EUW1_7685543426",
            "time": "2026-01-14T21:38:26.873Z",
            "win": true,
            "championId": 202,
            "championName": "Jhin",
            "championIcon": "https://ddragon.leagueoflegends.com/cdn/16.1.1/img/champion/Jhin.png",
            "k": 14,
            "d": 3,
            "a": 6,
            "durationSec": 1598,
            "queueId": 420
          },
          {
            "matchId": "EUW1_7685423730",
            "time": "2026-01-14T20:35:26.951Z",
            "win": true,
            "championId": 51,
            "championName": "Caitlyn",
            "championIcon": "https://ddragon.leagueoflegends.com/cdn/16.1.1/img/champion/Caitlyn.png",
            "k": 6,
            "d": 2,
            "a": 3,
            "durationSec": 1613,
            "queueId": 420
          },
          {
            "matchId": "EUW1_7684145152",
            "time": "2026-01-13T21:36:26.204Z",
            "win": true,
            "championId": 21,
            "championName": "Miss Fortune",
            "championIcon": "https://ddragon.leagueoflegends.com/cdn/16.1.1/img/champion/MissFortune.png",
            "k": 26,
            "d": 6,
            "a": 8,
            "durationSec": 2263,
            "queueId": 420
          },
          {
            "matchId": "EUW1_7684058393",
            "time": "2026-01-13T20:54:17.302Z",
            "win": true,
            "championId": 51,
            "championName": "Caitlyn",
            "championIcon": "https://ddragon.leagueoflegends.com/cdn/16.1.1/img/champion/Caitlyn.png",
            "k": 19,
            "d": 5,
            "a": 5,
            "durationSec": 2040,
            "queueId": 420
          },
          {
            "matchId": "EUW1_7683993033",
            "time": "2026-01-13T20:14:49.953Z",
            "win": false,
            "championId": 18,
            "championName": "Tristana",
            "championIcon": "https://ddragon.leagueoflegends.com/cdn/16.1.1/img/champion/Tristana.png",
            "k": 2,
            "d": 3,
            "a": 4,
            "durationSec": 1633,
            "queueId": 420
          }
        ]
      },
      "soloWL": {
        "wins": 7,
        "losses": 6
      }
    },
    {
      "id": "p2",
      "displayName": "Selim",
      "platform": "euw1",
      "riotId": {
        "gameName": "KnopfDonald",
        "tagLine": "Marv"
      },
      "puuid": "GXD6AEJBvLiz7nXkcBcudjTlkTBfAYpChkZpHv6XMA_K4KrHU_SbJPURezb39KXXwJ0sTAW6kk6kyA",
      "lastRank": {
        "tier": "SILVER",
        "division": "IV",
        "lp": 80,
        "wins": 19,
        "losses": 7,
        "winrate": 73.1
      },
      "currentRank": {
        "tier": "SILVER",
        "division": "IV",
        "lp": 80,
        "wins": 19,
        "losses": 7,
        "winrate": 73.1
      },
      "bans": [
        {
          "time": "2026-01-13T12:34:56.000Z",
          "champion": "Tristana",
          "note": "Von Bronze 3 nach 2"
        },
        {
          "time": "2026-01-13T12:34:56.000Z",
          "champion": "Miss Fortune",
          "note": "Von Bronze 3 nach 2"
        },
        {
          "time": "2026-01-13T12:34:56.000Z",
          "champion": "Nunu & Willump",
          "note": "Von Bronze 3 nach 2"
        },
        {
          "time": "2026-01-14T12:34:56.000Z",
          "champion": "Viego",
          "note": "Von Bronze 3 nach 2"
        }
      ],
      "pendingBan": null,
      "lastUpdatedAt": "2026-01-16T17:16:24.978Z",
      "champGamesByYear": {
        "2026": {
          "computedAt": "2026-01-16T16:54:39.981Z",
          "year": 2026,
          "queueId": 420,
          "matchCount": 26,
          "totalGames": 26,
          "latestMatchId": "EUW1_7687147541",
          "countsByChampionId": {
            "11": 1,
            "18": 7,
            "20": 2,
            "21": 2,
            "39": 1,
            "122": 1,
            "141": 1,
            "166": 1,
            "203": 1,
            "233": 1,
            "234": 3,
            "711": 1,
            "777": 1,
            "876": 2,
            "893": 1
          },
          "byChampion": [
            {
              "championId": 18,
              "count": 7,
              "name": "Tristana",
              "icon": "https://ddragon.leagueoflegends.com/cdn/16.1.1/img/champion/Tristana.png"
            },
            {
              "championId": 234,
              "count": 3,
              "name": "Viego",
              "icon": "https://ddragon.leagueoflegends.com/cdn/16.1.1/img/champion/Viego.png"
            },
            {
              "championId": 20,
              "count": 2,
              "name": "Nunu & Willump",
              "icon": "https://ddragon.leagueoflegends.com/cdn/16.1.1/img/champion/Nunu.png"
            },
            {
              "championId": 21,
              "count": 2,
              "name": "Miss Fortune",
              "icon": "https://ddragon.leagueoflegends.com/cdn/16.1.1/img/champion/MissFortune.png"
            },
            {
              "championId": 876,
              "count": 2,
              "name": "Lillia",
              "icon": "https://ddragon.leagueoflegends.com/cdn/16.1.1/img/champion/Lillia.png"
            },
            {
              "championId": 11,
              "count": 1,
              "name": "Master Yi",
              "icon": "https://ddragon.leagueoflegends.com/cdn/16.1.1/img/champion/MasterYi.png"
            },
            {
              "championId": 39,
              "count": 1,
              "name": "Irelia",
              "icon": "https://ddragon.leagueoflegends.com/cdn/16.1.1/img/champion/Irelia.png"
            },
            {
              "championId": 122,
              "count": 1,
              "name": "Darius",
              "icon": "https://ddragon.leagueoflegends.com/cdn/16.1.1/img/champion/Darius.png"
            },
            {
              "championId": 141,
              "count": 1,
              "name": "Kayn",
              "icon": "https://ddragon.leagueoflegends.com/cdn/16.1.1/img/champion/Kayn.png"
            },
            {
              "championId": 166,
              "count": 1,
              "name": "Akshan",
              "icon": "https://ddragon.leagueoflegends.com/cdn/16.1.1/img/champion/Akshan.png"
            },
            {
              "championId": 203,
              "count": 1,
              "name": "Kindred",
              "icon": "https://ddragon.leagueoflegends.com/cdn/16.1.1/img/champion/Kindred.png"
            },
            {
              "championId": 233,
              "count": 1,
              "name": "Briar",
              "icon": "https://ddragon.leagueoflegends.com/cdn/16.1.1/img/champion/Briar.png"
            },
            {
              "championId": 711,
              "count": 1,
              "name": "Vex",
              "icon": "https://ddragon.leagueoflegends.com/cdn/16.1.1/img/champion/Vex.png"
            },
            {
              "championId": 777,
              "count": 1,
              "name": "Yone",
              "icon": "https://ddragon.leagueoflegends.com/cdn/16.1.1/img/champion/Yone.png"
            },
            {
              "championId": 893,
              "count": 1,
              "name": "Aurora",
              "icon": "https://ddragon.leagueoflegends.com/cdn/16.1.1/img/champion/Aurora.png"
            }
          ],
          "triggerSoloTotal": 26
        }
      },
      "last5": {
        "computedAt": "2026-01-16T16:54:38.745Z",
        "games": [
          {
            "matchId": "EUW1_7687147541",
            "time": "2026-01-15T23:31:41.381Z",
            "win": true,
            "championId": 166,
            "championName": "Akshan",
            "championIcon": "https://ddragon.leagueoflegends.com/cdn/16.1.1/img/champion/Akshan.png",
            "k": 6,
            "d": 5,
            "a": 15,
            "durationSec": 1875,
            "queueId": 420
          },
          {
            "matchId": "EUW1_7687088621",
            "time": "2026-01-15T22:55:31.504Z",
            "win": true,
            "championId": 893,
            "championName": "Aurora",
            "championIcon": "https://ddragon.leagueoflegends.com/cdn/16.1.1/img/champion/Aurora.png",
            "k": 3,
            "d": 5,
            "a": 7,
            "durationSec": 1894,
            "queueId": 420
          },
          {
            "matchId": "EUW1_7686562423",
            "time": "2026-01-15T18:56:17.111Z",
            "win": false,
            "championId": 777,
            "championName": "Yone",
            "championIcon": "https://ddragon.leagueoflegends.com/cdn/16.1.1/img/champion/Yone.png",
            "k": 3,
            "d": 8,
            "a": 1,
            "durationSec": 1500,
            "queueId": 420
          },
          {
            "matchId": "EUW1_7684998295",
            "time": "2026-01-14T16:28:36.163Z",
            "win": true,
            "championId": 711,
            "championName": "Vex",
            "championIcon": "https://ddragon.leagueoflegends.com/cdn/16.1.1/img/champion/Vex.png",
            "k": 2,
            "d": 9,
            "a": 8,
            "durationSec": 1957,
            "queueId": 420
          },
          {
            "matchId": "EUW1_7684965232",
            "time": "2026-01-14T15:51:01.073Z",
            "win": false,
            "championId": 39,
            "championName": "Irelia",
            "championIcon": "https://ddragon.leagueoflegends.com/cdn/16.1.1/img/champion/Irelia.png",
            "k": 6,
            "d": 3,
            "a": 1,
            "durationSec": 1269,
            "queueId": 420
          }
        ]
      },
      "soloWL": {
        "wins": 19,
        "losses": 7
      }
    },
    {
      "id": "p3",
      "displayName": "Roman",
      "platform": "euw1",
      "riotId": {
        "gameName": "Ratzefummel",
        "tagLine": "1111"
      },
      "puuid": "zi2_72d0jxWZ9hI1oIyDgBeGvxR7VuIwG48K83E5PJya4na_LqVx1McVvJkDJnDJkYgeiktUx6-Zow",
      "lastRank": {
        "tier": "SILVER",
        "division": "IV",
        "lp": 9,
        "wins": 16,
        "losses": 4,
        "winrate": 80
      },
      "currentRank": {
        "tier": "SILVER",
        "division": "IV",
        "lp": 9,
        "wins": 16,
        "losses": 4,
        "winrate": 80
      },
      "bans": [
        {
          "time": "2026-01-12T12:34:56.000Z",
          "champion": "Nilah",
          "note": "Von Bronze 3 nach 2"
        },
        {
          "time": "2026-01-16T11:34:56.000Z",
          "champion": "Miss Fortune",
          "note": ""
        },
        {
          "time": "2026-01-16T17:34:56.000Z",
          "champion": "Smolder",
          "note": ""
        }
      ],
      "pendingBan": null,
      "lastUpdatedAt": "2026-01-16T17:16:24.978Z",
      "champGamesByYear": {
        "2026": {
          "computedAt": "2026-01-16T16:54:40.757Z",
          "year": 2026,
          "queueId": 420,
          "matchCount": 21,
          "totalGames": 20,
          "latestMatchId": "EUW1_7687785887",
          "countsByChampionId": {
            "15": 1,
            "21": 2,
            "29": 1,
            "51": 1,
            "60": 1,
            "81": 1,
            "110": 2,
            "115": 1,
            "120": 1,
            "127": 1,
            "222": 2,
            "360": 1,
            "498": 1,
            "800": 1,
            "895": 1,
            "901": 2
          },
          "byChampion": [
            {
              "championId": 21,
              "count": 2,
              "name": "Miss Fortune",
              "icon": "https://ddragon.leagueoflegends.com/cdn/16.1.1/img/champion/MissFortune.png"
            },
            {
              "championId": 110,
              "count": 2,
              "name": "Varus",
              "icon": "https://ddragon.leagueoflegends.com/cdn/16.1.1/img/champion/Varus.png"
            },
            {
              "championId": 222,
              "count": 2,
              "name": "Jinx",
              "icon": "https://ddragon.leagueoflegends.com/cdn/16.1.1/img/champion/Jinx.png"
            },
            {
              "championId": 901,
              "count": 2,
              "name": "Smolder",
              "icon": "https://ddragon.leagueoflegends.com/cdn/16.1.1/img/champion/Smolder.png"
            },
            {
              "championId": 15,
              "count": 1,
              "name": "Sivir",
              "icon": "https://ddragon.leagueoflegends.com/cdn/16.1.1/img/champion/Sivir.png"
            },
            {
              "championId": 29,
              "count": 1,
              "name": "Twitch",
              "icon": "https://ddragon.leagueoflegends.com/cdn/16.1.1/img/champion/Twitch.png"
            },
            {
              "championId": 51,
              "count": 1,
              "name": "Caitlyn",
              "icon": "https://ddragon.leagueoflegends.com/cdn/16.1.1/img/champion/Caitlyn.png"
            },
            {
              "championId": 60,
              "count": 1,
              "name": "Elise",
              "icon": "https://ddragon.leagueoflegends.com/cdn/16.1.1/img/champion/Elise.png"
            },
            {
              "championId": 81,
              "count": 1,
              "name": "Ezreal",
              "icon": "https://ddragon.leagueoflegends.com/cdn/16.1.1/img/champion/Ezreal.png"
            },
            {
              "championId": 115,
              "count": 1,
              "name": "Ziggs",
              "icon": "https://ddragon.leagueoflegends.com/cdn/16.1.1/img/champion/Ziggs.png"
            },
            {
              "championId": 120,
              "count": 1,
              "name": "Hecarim",
              "icon": "https://ddragon.leagueoflegends.com/cdn/16.1.1/img/champion/Hecarim.png"
            },
            {
              "championId": 127,
              "count": 1,
              "name": "Lissandra",
              "icon": "https://ddragon.leagueoflegends.com/cdn/16.1.1/img/champion/Lissandra.png"
            },
            {
              "championId": 360,
              "count": 1,
              "name": "Samira",
              "icon": "https://ddragon.leagueoflegends.com/cdn/16.1.1/img/champion/Samira.png"
            },
            {
              "championId": 498,
              "count": 1,
              "name": "Xayah",
              "icon": "https://ddragon.leagueoflegends.com/cdn/16.1.1/img/champion/Xayah.png"
            },
            {
              "championId": 800,
              "count": 1,
              "name": "Mel",
              "icon": "https://ddragon.leagueoflegends.com/cdn/16.1.1/img/champion/Mel.png"
            },
            {
              "championId": 895,
              "count": 1,
              "name": "Nilah",
              "icon": "https://ddragon.leagueoflegends.com/cdn/16.1.1/img/champion/Nilah.png"
            }
          ],
          "triggerSoloTotal": 20
        }
      },
      "last5": {
        "computedAt": "2026-01-16T16:54:38.745Z",
        "games": [
          {
            "matchId": "EUW1_7687785887",
            "time": "2026-01-16T16:18:23.752Z",
            "win": true,
            "championId": 901,
            "championName": "Smolder",
            "championIcon": "https://ddragon.leagueoflegends.com/cdn/16.1.1/img/champion/Smolder.png",
            "k": 11,
            "d": 4,
            "a": 11,
            "durationSec": 1643,
            "queueId": 420
          },
          {
            "matchId": "EUW1_7687741896",
            "time": "2026-01-16T15:45:45.643Z",
            "win": true,
            "championId": 901,
            "championName": "Smolder",
            "championIcon": "https://ddragon.leagueoflegends.com/cdn/16.1.1/img/champion/Smolder.png",
            "k": 4,
            "d": 3,
            "a": 7,
            "durationSec": 1779,
            "queueId": 420
          },
          {
            "matchId": "EUW1_7687685116",
            "time": "2026-01-16T15:12:51.178Z",
            "win": false,
            "championId": 60,
            "championName": "Elise",
            "championIcon": "https://ddragon.leagueoflegends.com/cdn/16.1.1/img/champion/Elise.png",
            "k": 13,
            "d": 6,
            "a": 16,
            "durationSec": 2081,
            "queueId": 420
          },
          {
            "matchId": "EUW1_7687655798",
            "time": "2026-01-16T14:31:22.288Z",
            "win": true,
            "championId": 222,
            "championName": "Jinx",
            "championIcon": "https://ddragon.leagueoflegends.com/cdn/16.1.1/img/champion/Jinx.png",
            "k": 6,
            "d": 3,
            "a": 6,
            "durationSec": 1271,
            "queueId": 420
          },
          {
            "matchId": "EUW1_7687610124",
            "time": "2026-01-16T14:04:40.843Z",
            "win": false,
            "championId": 127,
            "championName": "Lissandra",
            "championIcon": "https://ddragon.leagueoflegends.com/cdn/16.1.1/img/champion/Lissandra.png",
            "k": 5,
            "d": 7,
            "a": 15,
            "durationSec": 2042,
            "queueId": 420
          }
        ]
      },
      "soloWL": {
        "wins": 16,
        "losses": 4
      }
    },
    {
      "id": "p4",
      "displayName": "Darwin",
      "platform": "euw1",
      "riotId": {
        "gameName": "Dave",
        "tagLine": "darw"
      },
      "puuid": "mPGCFfPxPgsVVmrYUhp9K_X6NNCtMP4ugLfwd6cOogf4XlgQXtAd8bD2xCIO3X_9jVHVBHdDrbuXpA",
      "lastRank": {
        "tier": "BRONZE",
        "division": "II",
        "lp": 58,
        "wins": 13,
        "losses": 11,
        "winrate": 54.2
      },
      "currentRank": {
        "tier": "BRONZE",
        "division": "II",
        "lp": 58,
        "wins": 13,
        "losses": 11,
        "winrate": 54.2
      },
      "bans": [
        {
          "time": "2026-01-12T12:34:56.000Z",
          "champion": "Morgana",
          "note": "Von Bronze 4 nach 3"
        },
        {
          "time": "2026-01-14T12:34:56.000Z",
          "champion": "Elise",
          "note": "Von Bronze 3 nach 2"
        },
        {
          "time": "2026-01-14T12:34:56.000Z",
          "champion": "Kindred",
          "note": "Von Bronze 2 nach 1"
        }
      ],
      "pendingBan": null,
      "lastUpdatedAt": "2026-01-16T17:16:24.978Z",
      "champGamesByYear": {
        "2026": {
          "computedAt": "2026-01-16T16:54:41.639Z",
          "year": 2026,
          "queueId": 420,
          "matchCount": 28,
          "totalGames": 23,
          "latestMatchId": "EUW1_7687805161",
          "countsByChampionId": {
            "15": 1,
            "18": 1,
            "21": 1,
            "25": 4,
            "51": 1,
            "60": 4,
            "63": 1,
            "81": 1,
            "84": 1,
            "143": 2,
            "202": 1,
            "203": 1,
            "236": 1,
            "360": 1,
            "523": 1,
            "876": 1
          },
          "byChampion": [
            {
              "championId": 25,
              "count": 4,
              "name": "Morgana",
              "icon": "https://ddragon.leagueoflegends.com/cdn/16.1.1/img/champion/Morgana.png"
            },
            {
              "championId": 60,
              "count": 4,
              "name": "Elise",
              "icon": "https://ddragon.leagueoflegends.com/cdn/16.1.1/img/champion/Elise.png"
            },
            {
              "championId": 143,
              "count": 2,
              "name": "Zyra",
              "icon": "https://ddragon.leagueoflegends.com/cdn/16.1.1/img/champion/Zyra.png"
            },
            {
              "championId": 15,
              "count": 1,
              "name": "Sivir",
              "icon": "https://ddragon.leagueoflegends.com/cdn/16.1.1/img/champion/Sivir.png"
            },
            {
              "championId": 18,
              "count": 1,
              "name": "Tristana",
              "icon": "https://ddragon.leagueoflegends.com/cdn/16.1.1/img/champion/Tristana.png"
            },
            {
              "championId": 21,
              "count": 1,
              "name": "Miss Fortune",
              "icon": "https://ddragon.leagueoflegends.com/cdn/16.1.1/img/champion/MissFortune.png"
            },
            {
              "championId": 51,
              "count": 1,
              "name": "Caitlyn",
              "icon": "https://ddragon.leagueoflegends.com/cdn/16.1.1/img/champion/Caitlyn.png"
            },
            {
              "championId": 63,
              "count": 1,
              "name": "Brand",
              "icon": "https://ddragon.leagueoflegends.com/cdn/16.1.1/img/champion/Brand.png"
            },
            {
              "championId": 81,
              "count": 1,
              "name": "Ezreal",
              "icon": "https://ddragon.leagueoflegends.com/cdn/16.1.1/img/champion/Ezreal.png"
            },
            {
              "championId": 84,
              "count": 1,
              "name": "Akali",
              "icon": "https://ddragon.leagueoflegends.com/cdn/16.1.1/img/champion/Akali.png"
            },
            {
              "championId": 202,
              "count": 1,
              "name": "Jhin",
              "icon": "https://ddragon.leagueoflegends.com/cdn/16.1.1/img/champion/Jhin.png"
            },
            {
              "championId": 203,
              "count": 1,
              "name": "Kindred",
              "icon": "https://ddragon.leagueoflegends.com/cdn/16.1.1/img/champion/Kindred.png"
            },
            {
              "championId": 236,
              "count": 1,
              "name": "Lucian",
              "icon": "https://ddragon.leagueoflegends.com/cdn/16.1.1/img/champion/Lucian.png"
            },
            {
              "championId": 360,
              "count": 1,
              "name": "Samira",
              "icon": "https://ddragon.leagueoflegends.com/cdn/16.1.1/img/champion/Samira.png"
            },
            {
              "championId": 523,
              "count": 1,
              "name": "Aphelios",
              "icon": "https://ddragon.leagueoflegends.com/cdn/16.1.1/img/champion/Aphelios.png"
            },
            {
              "championId": 876,
              "count": 1,
              "name": "Lillia",
              "icon": "https://ddragon.leagueoflegends.com/cdn/16.1.1/img/champion/Lillia.png"
            }
          ],
          "triggerSoloTotal": 24
        }
      },
      "last5": {
        "computedAt": "2026-01-16T16:52:53.489Z",
        "games": [
          {
            "matchId": "EUW1_7687805161",
            "time": "2026-01-16T16:44:38.937Z",
            "win": false,
            "championId": 360,
            "championName": "Samira",
            "championIcon": "https://ddragon.leagueoflegends.com/cdn/16.1.1/img/champion/Samira.png",
            "k": 16,
            "d": 9,
            "a": 7,
            "durationSec": 2347,
            "queueId": 420
          },
          {
            "matchId": "EUW1_7687750171",
            "time": "2026-01-16T15:51:15.444Z",
            "win": false,
            "championId": 18,
            "championName": "Tristana",
            "championIcon": "https://ddragon.leagueoflegends.com/cdn/16.1.1/img/champion/Tristana.png",
            "k": 5,
            "d": 10,
            "a": 4,
            "durationSec": 1511,
            "queueId": 420
          },
          {
            "matchId": "EUW1_7687684621",
            "time": "2026-01-16T15:10:12.319Z",
            "win": true,
            "championId": 15,
            "championName": "Sivir",
            "championIcon": "https://ddragon.leagueoflegends.com/cdn/16.1.1/img/champion/Sivir.png",
            "k": 6,
            "d": 8,
            "a": 9,
            "durationSec": 2195,
            "queueId": 420
          },
          {
            "matchId": "EUW1_7687439107",
            "time": "2026-01-16T10:35:29.879Z",
            "win": false,
            "championId": 236,
            "championName": "Lucian",
            "championIcon": "https://ddragon.leagueoflegends.com/cdn/16.1.1/img/champion/Lucian.png",
            "k": 8,
            "d": 6,
            "a": 5,
            "durationSec": 1767,
            "queueId": 420
          },
          {
            "matchId": "EUW1_7687086405",
            "time": "2026-01-15T23:18:45.755Z",
            "win": false,
            "championId": 21,
            "championName": "Miss Fortune",
            "championIcon": "https://ddragon.leagueoflegends.com/cdn/16.1.1/img/champion/MissFortune.png",
            "k": 23,
            "d": 10,
            "a": 15,
            "durationSec": 3036,
            "queueId": 420
          }
        ]
      },
      "soloWL": {
        "wins": 13,
        "losses": 11
      }
    },
    {
      "id": "p5",
      "displayName": "Marvin",
      "platform": "euw1",
      "riotId": {
        "gameName": "MurmelUrmel",
        "tagLine": "lost"
      },
      "puuid": "hcfobvDsSX9QzWLs0dxPXkAK8NOEvcM55FrnxFgQT5CgBI0NPo0Mn9DYvKFGVmVbSj33BTngXEeGWw",
      "lastRank": {
        "tier": "BRONZE",
        "division": "IV",
        "lp": 58,
        "wins": 6,
        "losses": 5,
        "winrate": 54.5
      },
      "currentRank": {
        "tier": "BRONZE",
        "division": "IV",
        "lp": 58,
        "wins": 6,
        "losses": 5,
        "winrate": 54.5
      },
      "bans": [],
      "pendingBan": null,
      "lastUpdatedAt": "2026-01-16T17:16:24.978Z",
      "champGamesByYear": {
        "2026": {
          "computedAt": "2026-01-16T16:53:09.466Z",
          "year": 2026,
          "queueId": 420,
          "matchCount": 11,
          "totalGames": 11,
          "latestMatchId": "EUW1_7682905204",
          "countsByChampionId": {
            "33": 1,
            "34": 1,
            "38": 2,
            "45": 4,
            "105": 3
          },
          "byChampion": [
            {
              "championId": 45,
              "count": 4,
              "name": "Veigar",
              "icon": "https://ddragon.leagueoflegends.com/cdn/16.1.1/img/champion/Veigar.png"
            },
            {
              "championId": 105,
              "count": 3,
              "name": "Fizz",
              "icon": "https://ddragon.leagueoflegends.com/cdn/16.1.1/img/champion/Fizz.png"
            },
            {
              "championId": 38,
              "count": 2,
              "name": "Kassadin",
              "icon": "https://ddragon.leagueoflegends.com/cdn/16.1.1/img/champion/Kassadin.png"
            },
            {
              "championId": 33,
              "count": 1,
              "name": "Rammus",
              "icon": "https://ddragon.leagueoflegends.com/cdn/16.1.1/img/champion/Rammus.png"
            },
            {
              "championId": 34,
              "count": 1,
              "name": "Anivia",
              "icon": "https://ddragon.leagueoflegends.com/cdn/16.1.1/img/champion/Anivia.png"
            }
          ],
          "triggerSoloTotal": 11
        }
      },
      "last5": {
        "computedAt": "2026-01-16T16:53:09.466Z",
        "games": [
          {
            "matchId": "EUW1_7682905204",
            "time": "2026-01-12T22:59:03.692Z",
            "win": false,
            "championId": 38,
            "championName": "Kassadin",
            "championIcon": "https://ddragon.leagueoflegends.com/cdn/16.1.1/img/champion/Kassadin.png",
            "k": 20,
            "d": 4,
            "a": 14,
            "durationSec": 2219,
            "queueId": 420
          },
          {
            "matchId": "EUW1_7682806248",
            "time": "2026-01-12T22:03:12.908Z",
            "win": true,
            "championId": 38,
            "championName": "Kassadin",
            "championIcon": "https://ddragon.leagueoflegends.com/cdn/16.1.1/img/champion/Kassadin.png",
            "k": 19,
            "d": 5,
            "a": 8,
            "durationSec": 1938,
            "queueId": 420
          },
          {
            "matchId": "EUW1_7682719990",
            "time": "2026-01-12T21:20:37.669Z",
            "win": false,
            "championId": 45,
            "championName": "Veigar",
            "championIcon": "https://ddragon.leagueoflegends.com/cdn/16.1.1/img/champion/Veigar.png",
            "k": 0,
            "d": 6,
            "a": 4,
            "durationSec": 1800,
            "queueId": 420
          },
          {
            "matchId": "EUW1_7682371151",
            "time": "2026-01-12T18:37:07.216Z",
            "win": false,
            "championId": 45,
            "championName": "Veigar",
            "championIcon": "https://ddragon.leagueoflegends.com/cdn/16.1.1/img/champion/Veigar.png",
            "k": 10,
            "d": 10,
            "a": 6,
            "durationSec": 2127,
            "queueId": 420
          },
          {
            "matchId": "EUW1_7682297782",
            "time": "2026-01-12T17:52:43.413Z",
            "win": true,
            "championId": 45,
            "championName": "Veigar",
            "championIcon": "https://ddragon.leagueoflegends.com/cdn/16.1.1/img/champion/Veigar.png",
            "k": 10,
            "d": 6,
            "a": 9,
            "durationSec": 2214,
            "queueId": 420
          }
        ]
      },
      "soloWL": {
        "wins": 6,
        "losses": 5
      }
    }
  ],
  "banHistory": [
    {
      "time": "2026-01-16T17:34:56.000Z",
      "playerId": "p3",
      "playerName": "Roman",
      "champion": "Smolder",
      "note": "",
      "promotion": {
        "from": {
          "tier": "BRONZE",
          "division": "III",
          "lp": 81
        },
        "to": {
          "tier": "BRONZE",
          "division": "II",
          "lp": 11
        },
        "detectedAt": "2026-01-10T18:35:00.000Z"
      }
    },
    {
      "time": "2026-01-16T11:34:56.000Z",
      "playerId": "p3",
      "playerName": "Roman",
      "champion": "Miss Fortune",
      "note": "",
      "promotion": {
        "from": {
          "tier": "BRONZE",
          "division": "II",
          "lp": 84
        },
        "to": {
          "tier": "BRONZE",
          "division": "I",
          "lp": 14
        },
        "detectedAt": "2026-01-10T18:35:00.000Z"
      }
    },
    {
      "time": "2026-01-14T22:34:56.000Z",
      "playerId": "p1",
      "playerName": "Vincent",
      "champion": "Caitlyn",
      "note": "",
      "promotion": {
        "from": {
          "tier": "BRONZE",
          "division": "IV",
          "lp": 89
        },
        "to": {
          "tier": "BRONZE",
          "division": "III",
          "lp": 19
        },
        "detectedAt": "2026-01-10T18:35:00.000Z"
      }
    },
    {
      "time": "2026-01-14T17:34:56.000Z",
      "playerId": "p4",
      "playerName": "Darwin",
      "champion": "Kindred",
      "note": "",
      "promotion": {
        "from": {
          "tier": "BRONZE",
          "division": "II",
          "lp": 71
        },
        "to": {
          "tier": "BRONZE",
          "division": "I",
          "lp": 1
        },
        "detectedAt": "2026-01-10T18:35:00.000Z"
      }
    },
    {
      "time": "2026-01-14T14:52:56.000Z",
      "playerId": "p2",
      "playerName": "Selim",
      "champion": "Viego",
      "note": "",
      "promotion": {
        "from": {
          "tier": "BRONZE",
          "division": "I",
          "lp": 71
        },
        "to": {
          "tier": "SILVER",
          "division": "IV",
          "lp": 1
        },
        "detectedAt": "2026-01-13T20:35:00.000Z"
      }
    },
    {
      "time": "2026-01-14T14:34:56.000Z",
      "playerId": "p4",
      "playerName": "Darwin",
      "champion": "Elise",
      "note": "",
      "promotion": {
        "from": {
          "tier": "BRONZE",
          "division": "III",
          "lp": 81
        },
        "to": {
          "tier": "BRONZE",
          "division": "II",
          "lp": 11
        },
        "detectedAt": "2026-01-10T18:35:00.000Z"
      }
    },
    {
      "time": "2026-01-13T22:21:56.000Z",
      "playerId": "p2",
      "playerName": "Selim",
      "champion": "Nunu & Willump",
      "note": "",
      "promotion": {
        "from": {
          "tier": "BRONZE",
          "division": "II",
          "lp": 81
        },
        "to": {
          "tier": "BRONZE",
          "division": "I",
          "lp": 11
        },
        "detectedAt": "2026-01-13T20:35:00.000Z"
      }
    },
    {
      "time": "2026-01-13T20:41:56.000Z",
      "playerId": "p2",
      "playerName": "Selim",
      "champion": "Miss Fortune",
      "note": "",
      "promotion": {
        "from": {
          "tier": "BRONZE",
          "division": "II",
          "lp": 71
        },
        "to": {
          "tier": "BRONZE",
          "division": "I",
          "lp": 1
        },
        "detectedAt": "2026-01-13T20:35:00.000Z"
      }
    },
    {
      "time": "2026-01-13T12:34:56.000Z",
      "playerId": "p2",
      "playerName": "Selim",
      "champion": "Tristana",
      "note": "",
      "promotion": {
        "from": {
          "tier": "BRONZE",
          "division": "III",
          "lp": 70
        },
        "to": {
          "tier": "BRONZE",
          "division": "II",
          "lp": 1
        },
        "detectedAt": "2026-01-13T20:35:00.000Z"
      }
    },
    {
      "time": "2026-01-12T12:34:56.000Z",
      "playerId": "p4",
      "playerName": "Darwin",
      "champion": "Morgana",
      "note": "",
      "promotion": {
        "from": {
          "tier": "BRONZE",
          "division": "IV",
          "lp": 75
        },
        "to": {
          "tier": "BRONZE",
          "division": "III",
          "lp": 15
        },
        "detectedAt": "2026-01-10T18:35:00.000Z"
      }
    },
    {
      "time": "2026-01-12T12:34:56.000Z",
      "playerId": "p3",
      "playerName": "Roman",
      "champion": "Nilah",
      "note": "",
      "promotion": {
        "from": {
          "tier": "BRONZE",
          "division": "III",
          "lp": 75
        },
        "to": {
          "tier": "BRONZE",
          "division": "II",
          "lp": 15
        },
        "detectedAt": "2026-01-10T18:35:00.000Z"
      }
    }
  ]
}
